pydisney/Auth.py
pydisney/Config.py
pydisney/DisneyAPI.py
pydisney/Exceptions.py
pydisney/__init__.py
pydisney/models/Account.py
pydisney/models/Downloable.py
pydisney/models/Episode.py
pydisney/models/Hit.py
pydisney/models/Language.py
pydisney/models/LanguagePreferences.py
pydisney/models/Profile.py
pydisney/models/ProgramType.py
pydisney/models/Rating.py
pydisney/models/Season.py
pydisney/models/__init__.py
pydisney/utils/__init__.py
pydisney/utils/helper.py
pydisney/utils/parser.py
pydisney-3.0.2.dist-info/licenses/LICENSE
pydisney-3.0.2.dist-info/METADATA
pydisney-3.0.2.dist-info/WHEEL
pydisney-3.0.2.dist-info/top_level.txt
pydisney-3.0.2.dist-info/RECORD
