Metadata-Version: 2.4
Name: pydisney
Version: 3.0.2
Summary: A Feature rich API wrapper for Disney+ made with python. Allows for subtitle and audio download
Author: Pamparampampam
License: MIT License
Project-URL: Github, https://github.com/pam-param-pam/Disney-Plus-api-wrapper
Keywords: disney,disneyplus,api,wrapper,client,python,pydisney,subtitle,subtitle-downloader,downloader,disney+
Classifier: License :: OSI Approved :: MIT License
Classifier: Programming Language :: Python
Classifier: Programming Language :: Python :: 3
Requires-Python: >=3.7
License-File: LICENSE
Requires-Dist: requests>=2.32.3
Requires-Dist: m3u8>=3.6.0
Dynamic: license-file
